epmanager/__init__.py
epmanager/discovery.py
epmanager/dispatcher.py
epmanager/examples.py
epmanager/main.py
epmanager/parser.py
epmanager-0.7.5.dist-info/entry_points.txt
epmanager-0.7.5.dist-info/LICENSE
epmanager-0.7.5.dist-info/WHEEL
epmanager-0.7.5.dist-info/METADATA
epmanager-0.7.5.dist-info/RECORD
