Metadata-Version: 2.1
Name: epmanager
Version: 0.7.5
Summary: An entry-point management system for projects using Poetry
Home-page: https://github.com/zahlman/epmanager
License: MIT
Author: Karl Knechtel
Author-email: karl.a.knechtel@gmail.com
Requires-Python: >=3.6,<4.0
Classifier: License :: OSI Approved :: MIT License
Classifier: Programming Language :: Python :: 3
Classifier: Programming Language :: Python :: 3.6
Classifier: Programming Language :: Python :: 3.7
Classifier: Programming Language :: Python :: 3.8
Requires-Dist: toml (>=0.10.1,<0.11.0)
Project-URL: Documentation, https://github.com/zahlman/epmanager
Project-URL: Repository, https://github.com/zahlman/epmanager
